Workbook

Sheet INVEST
B11: CONFIGURACOES
B12: Salario | D12: 4200
B13: Rendimento Carteira | D13: 0.006
B14: Sugestao de Investimento (30%) | D14: =D12*30% -> 1260
B16: INVESTIMENTO MENSAL
B17: Quanto investir por mes? | D17: 200
B18: Por Quantos Anos? | D18: 5
B19: Taxa de Rendimiento mensal? | D19: 0.01079
B20: Patrimonio Acumulado? | D20: =FV(D19,D18*12,D17*-1) -> 16755.383
B21: Dividendos Mensais? | D21: =D20*D13 -> 100.5323
B23: Cenarios | D23: Dividendo
A24: 2 | B24: Quanto em 2 Anos? | C24: =FV($D$19,$A24*12,$D$17*-1) -> 5445.5255 | D24: =C24*$D$13 -> 32.673153
A25: 5 | B25: Quanto em 5 Anos? | C25: =FV($D$19,$A25*12,$D$17*-1) -> 16755.383 | D25: =C25*$D$13 -> 100.5323
A26: 10 | B26: Quanto em 10 Anos? | C26: =FV($D$19,$A26*12,$D$17*-1) -> 48656.843 | D26: =C26*$D$13 -> 291.94106
A27: 20 | B27: Quanto em 20 Anos? | C27: =FV($D$19,$A27*12,$D$17*-1) -> 225039.68 | D27: =C27*$D$13 -> 1350.2381
A28: 30 | B28: Quanto em 30 Anos? | C28: =FV($D$19,$A28*12,$D$17*-1) -> 864433.93 | D28: =C28*$D$13 -> 5186.6036
B32: PERFIL | C32: MODERADO
B33: VALOR A SER INVESTIDO POR MES | C33: =D17 -> 200
B35: TIPO DE FII | C35: Percentual Sugerido | D35: Valores
B36: PAPEL | C36: =VLOOKUP($C$32&"-"&B36,Planilha2!$A:$D,4,FALSE) -> 0.32 | D36: =C36*$C$33 -> 64
B37: TIOJOLO | C37: =VLOOKUP($C$32&"-"&B37,Planilha2!$A:$D,4,FALSE) -> 0.35 | D37: =C37*$C$33 -> 70
B38: HIBRIDOS | C38: =VLOOKUP($C$32&"-"&B38,Planilha2!$A:$D,4,FALSE) -> 0.08 | D38: =C38*$C$33 -> 16
B39: FOFs | C39: =VLOOKUP($C$32&"-"&B39,Planilha2!$A:$D,4,FALSE) -> 0.1 | D39: =C39*$C$33 -> 20
B40: DESENVOLVIMENTO | C40: =VLOOKUP($C$32&"-"&B40,Planilha2!$A:$D,4,FALSE) -> 0.05 | D40: =C40*$C$33 -> 10
B41: HOTELARIAS | C41: =VLOOKUP($C$32&"-"&B41,Planilha2!$A:$D,4,FALSE) -> 0.1 | D41: =C41*$C$33 -> 20
D42: =SUM(D36:E41) -> 200

Sheet Planilha2
A2: chave | B2: PERFIL | C2: TIPO DE FII | D2: %
A3: =B3&"-"&C3 -> CONSERVADOR-PAPEL | B3: CONSERVADOR | C3: PAPEL | D3: 0.3 | H3: %
A4: =B4&"-"&C4 -> CONSERVADOR-TIOJOLO | B4: CONSERVADOR | C4: TIOJOLO | D4: 0.5 | G4: MODERADO-TIOJOLO | H4: =VLOOKUP(G4,$A$1:$D$20,4,FALSE) -> 0.35
A5: =B5&"-"&C5 -> CONSERVADOR-HIBRIDOS | B5: CONSERVADOR | C5: HIBRIDOS | D5: 0.1
A6: =B6&"-"&C6 -> CONSERVADOR-FOFs | B6: CONSERVADOR | C6: FOFs | D6: 0.1
A7: =B7&"-"&C7 -> CONSERVADOR-DESENVOLVIMENTO | B7: CONSERVADOR | C7: DESENVOLVIMENTO | D7: 0
A8: =B8&"-"&C8 -> CONSERVADOR-HOTELARIAS | B8: CONSERVADOR | C8: HOTELARIAS | D8: 0
A9: =B9&"-"&C9 -> MODERADO-PAPEL | B9: MODERADO | C9: PAPEL | D9: 0.32
A10: =B10&"-"&C10 -> MODERADO-TIOJOLO | B10: MODERADO | C10: TIOJOLO | D10: 0.35
A11: =B11&"-"&C11 -> MODERADO-HIBRIDOS | B11: MODERADO | C11: HIBRIDOS | D11: 0.08
A12: =B12&"-"&C12 -> MODERADO-FOFs | B12: MODERADO | C12: FOFs | D12: 0.1
A13: =B13&"-"&C13 -> MODERADO-DESENVOLVIMENTO | B13: MODERADO | C13: DESENVOLVIMENTO | D13: 0.05
A14: =B14&"-"&C14 -> MODERADO-HOTELARIAS | B14: MODERADO | C14: HOTELARIAS | D14: 0.1
A15: =B15&"-"&C15 -> AGRESSIVO-PAPEL | B15: AGRESSIVO | C15: PAPEL | D15: 0.5
A16: =B16&"-"&C16 -> AGRESSIVO-TIOJOLO | B16: AGRESSIVO | C16: TIOJOLO | D16: 0.1
... A20: =B20&"-"&C20 -> AGRESSIVO-HOTELARIAS | B20: AGRESSIVO | C20: HOTELARIAS | D20: 0.1
